{
  "changefreq": { "type": "String", "default": null },
  "children": { "type": "Array", "default": [] },
  "description": { "type": "String", "default": null },
  "icon": { "type": "String", "default": null },
  "image": { "type": "String", "default": null },
  "keywords": { "type": "Array", "default": [] },
  "label": { "type": "String", "default": null },
  "lastmod": { "type": "String", "default": null },
  "loc": { "type": "String", "default": null },
  "priority": { "type": "Number", "default": null },
  "template": { "type": "String", "default": "" },
  "script": { "type": "String", "default": "" },
  "style": { "type": "String", "default": "" },
  "theme": { "type": "String", "default": "light" },
  "title": { "type": "String", "default": null },
  "visible": { "type": "Boolean", "default": true },
  "type": { "type": "String", "default": "website" },
  "alt": { "type": "String", "default": null },
  "full": { "type": "Boolean", "default": true },
  "setup": { "type": "Boolean", "default": true },
  "scoped": { "type": "Boolean", "default": true }
}
